README.rst
setup.cfg
setup.py
skillful/__init__.py
skillful/controller.py
skillful/interface.py
skillful/validate.py
skillful.egg-info/PKG-INFO
skillful.egg-info/SOURCES.txt
skillful.egg-info/dependency_links.txt
skillful.egg-info/requires.txt
skillful.egg-info/top_level.txt
skillful/tests/__init__.py
skillful/tests/data.py
skillful/tests/test_controller.py
skillful/tests/test_interface.py
skillful/tests/test_validate.py