Metadata-Version: 1.1
Name: skillful
Version: 0.8.2
Summary: A Python package for building Alexa skills.
Home-page: https://github.com/bmweiner/skillful
Author: bmweiner
Author-email: bmweiner@users.noreply.github.com
License: MIT License
Platform: py27
Platform: py35
Classifier: Topic :: Software Development :: Libraries :: Python Modules
Classifier: Topic :: Internet :: WWW/HTTP :: WSGI :: Application
Classifier: Environment :: Web Environment
Classifier: Intended Audience :: Developers
Classifier: Natural Language :: English
Classifier: Operating System :: OS Independent
Classifier: Programming Language :: Python
